<document>
<passage>
माँ ने वीरू को एक संदेश देकर अपनी बहन के पास भेजा। मौसी ने प्यार से वीरू को अंदर बुलाया और बैठक में ले गई। बैठक में कदम रखते ही वीरू अचरज से ठिठक गई। उसने सोचा- बाप रे! इतनी सारी किताबें!
</passage>
<anaphoraresolved>
माँ ने वीरू को एक संदेश देकर अपनी बहन के पास भेजा। मौसी ने प्यार से वीरू को अंदर बुलाया और बैठक में ले गई। बैठक में कदम रखते ही वीरू अचरज से ठिठक गई। वीरू ने सोचा- बाप रे! इतनी सारी किताबें!
</anaphoraresolved>
<stemmed>
माँ ने वीरू क एक संदेश दे अपन बहन क पास भेज। मौसी ने प्यार से वीरू को अंदर बुला और बैठ में ले ग। बैठ में कदम रख ही वीरू अचरज से ठिठक ग। वीरू ने सोच- बाप रे! इतन सार किताब!
</stemmed>
<qa>
<q>
माँ ने वीरू को क्या देकर अपनी बहन के पास भेजा ?
</q>
<a>
माँ ने वीरू को एक संदेश देकर अपनी बहन के पास भेजा।
</a>
<l> 1 </l>
</qa>

<qa>
<q>
मौसी ने किसे अंदर बुलाया ?
</q>
<a>
मौसी ने प्यार से वीरू को अंदर बुलाया और बैठक में ले गई। 
</a>
<l> 2 </l>
</qa>

<qa>
<q>
मौसी वीरू को कहाँ ले गई ?
</q>
<a>
मौसी ने प्यार से वीरू को अंदर बुलाया और बैठक में ले गई। 
</a>
<l> 2 </l>
</qa>

<qa>
<q>
 बैठक में कदम रखते ही कौन ठिठक गई ?
</q>
<a>
बैठक में कदम रखते ही वीरू अचरज से ठिठक गई।
</a>
<l> 3 </l>
</qa>

<qa>
<q>
वीरू ने क्या सोचा ?
</q>
<a>
उसने सोचा- बाप रे! इतनी सारी किताबें!
</a>
<l> 4 </l>
</qa>
</document>
